onnx_neural_compressor/__init__.py
onnx_neural_compressor/constants.py
onnx_neural_compressor/data_reader.py
onnx_neural_compressor/logger.py
onnx_neural_compressor/onnx_model.py
onnx_neural_compressor/utility.py
onnx_neural_compressor/version.py
onnx_neural_compressor/algorithms/__init__.py
onnx_neural_compressor/algorithms/utility.py
onnx_neural_compressor/algorithms/layer_wise/__init__.py
onnx_neural_compressor/algorithms/layer_wise/core.py
onnx_neural_compressor/algorithms/post_training_quant/__init__.py
onnx_neural_compressor/algorithms/post_training_quant/calibrate.py
onnx_neural_compressor/algorithms/post_training_quant/calibrator.py
onnx_neural_compressor/algorithms/post_training_quant/quantizer.py
onnx_neural_compressor/algorithms/post_training_quant/operators/__init__.py
onnx_neural_compressor/algorithms/post_training_quant/operators/activation.py
onnx_neural_compressor/algorithms/post_training_quant/operators/argmax.py
onnx_neural_compressor/algorithms/post_training_quant/operators/attention.py
onnx_neural_compressor/algorithms/post_training_quant/operators/base_op.py
onnx_neural_compressor/algorithms/post_training_quant/operators/binary_op.py
onnx_neural_compressor/algorithms/post_training_quant/operators/concat.py
onnx_neural_compressor/algorithms/post_training_quant/operators/conv.py
onnx_neural_compressor/algorithms/post_training_quant/operators/direct_q8.py
onnx_neural_compressor/algorithms/post_training_quant/operators/embed_layernorm.py
onnx_neural_compressor/algorithms/post_training_quant/operators/gather.py
onnx_neural_compressor/algorithms/post_training_quant/operators/gavgpool.py
onnx_neural_compressor/algorithms/post_training_quant/operators/gemm.py
onnx_neural_compressor/algorithms/post_training_quant/operators/lstm.py
onnx_neural_compressor/algorithms/post_training_quant/operators/matmul.py
onnx_neural_compressor/algorithms/post_training_quant/operators/maxpool.py
onnx_neural_compressor/algorithms/post_training_quant/operators/pad.py
onnx_neural_compressor-1.0.dist-info/LICENSE
onnx_neural_compressor-1.0.dist-info/METADATA
onnx_neural_compressor-1.0.dist-info/WHEEL
onnx_neural_compressor-1.0.dist-info/top_level.txt
onnx_neural_compressor-1.0.dist-info/RECORD
