Metadata-Version: 2.1
Name: onnx-neural-compressor
Version: 1.0
Summary: Repository of Neural Compressor ORT
Home-page: UNKNOWN
Author: Intel AIPT Team
Author-email: tai.huang@intel.com, mengni.wang@intel.com, yuwen.zhou@intel.com, suyue.chen@intel.com
License: Apache 2.0
Keywords: quantization
Platform: UNKNOWN
Classifier: Intended Audience :: Science/Research
Classifier: Programming Language :: Python :: 3
Classifier: Topic :: Scientific/Engineering :: Artificial Intelligence
Classifier: License :: OSI Approved :: Apache Software License
Requires-Python: >=3.8.0
Requires-Dist: onnx
Requires-Dist: onnxruntime
Requires-Dist: onnxruntime-extensions
Requires-Dist: psutil
Requires-Dist: numpy (<2.0.0)
Requires-Dist: py-cpuinfo
Requires-Dist: pydantic
Requires-Dist: transformers
